cone.zodb-1.0a3-py3.7-nspkg.pth
cone/zodb/__init__.py
cone/zodb/catalog.py
cone/zodb/common.py
cone/zodb/entry.py
cone/zodb/indexing.py
cone/zodb/interfaces.py
cone/zodb/testing.py
cone/zodb/tests/__init__.py
cone/zodb/tests/test_catalog.py
cone/zodb/tests/test_common.py
cone/zodb/tests/test_entry.py
cone/zodb/tests/test_indexing.py
cone.zodb-1.0a3.dist-info/LICENSE.rst
cone.zodb-1.0a3.dist-info/METADATA
cone.zodb-1.0a3.dist-info/WHEEL
cone.zodb-1.0a3.dist-info/namespace_packages.txt
cone.zodb-1.0a3.dist-info/top_level.txt
cone.zodb-1.0a3.dist-info/RECORD
