Metadata-Version: 2.1
Name: cone.zodb
Version: 1.0a3
Summary: ZODB integration for cone.app
Home-page: http://github.com/conestack/cone.zodb
Author: Cone Contributors
Author-email: dev@conestack.org
License: Simplified BSD
Keywords: node pyramid cone web
Platform: UNKNOWN
Classifier: Environment :: Web Environment
Classifier: Programming Language :: Python
Classifier: Topic :: Internet :: WWW/HTTP :: Dynamic Content
Requires-Dist: setuptools
Requires-Dist: node.ext.zodb
Requires-Dist: repoze.catalog
Requires-Dist: pyramid-tm
Requires-Dist: pyramid-zodbconn
Requires-Dist: cone.app
Provides-Extra: test
Requires-Dist: zope.testrunner ; extra == 'test'
